djangoarticle/__init__.py
djangoarticle/admin.py
djangoarticle/apps.py
djangoarticle/tests.py
djangoarticle/urls.py
djangoarticle/contexts/CategoryContext.py
djangoarticle/contexts/__init__.py
djangoarticle/contexts/__pycache__/CategoryContext.cpython-38.pyc
djangoarticle/contexts/__pycache__/__init__.cpython-38.pyc
djangoarticle/extra/ImageUploadDestination.py
djangoarticle/extra/__init__.py
djangoarticle/managers/ArticleModelSchemeManager.py
djangoarticle/managers/CategoryModelSchemeManager.py
djangoarticle/managers/__init__.py
djangoarticle/managers/__pycache__/ArticleModelSchemeManager.cpython-38.pyc
djangoarticle/managers/__pycache__/CategoryModelSchemeManager.cpython-38.pyc
djangoarticle/managers/__pycache__/__init__.cpython-38.pyc
djangoarticle/migrations/0001_initial.py
djangoarticle/migrations/__init__.py
djangoarticle/migrations/__pycache__/0001_initial.cpython-38.pyc
djangoarticle/migrations/__pycache__/__init__.cpython-38.pyc
djangoarticle/mixins/AdministratorAndOnlyAuthorAccess.py
djangoarticle/mixins/OnlyAdministratorAccess.py
djangoarticle/mixins/__init__.py
djangoarticle/mixins/__pycache__/AdministratorAndOnlyAuthorAccess.cpython-38.pyc
djangoarticle/mixins/__pycache__/OnlyAdministratorAccess.cpython-38.pyc
djangoarticle/mixins/__pycache__/__init__.cpython-38.pyc
djangoarticle/modeladmins/ArticleBookmarkModelSchemeAdmin.py
djangoarticle/modeladmins/ArticleModelSchemeAdmin.py
djangoarticle/modeladmins/CategoryModelSchemeAdmin.py
djangoarticle/modeladmins/__init__.py
djangoarticle/modeladmins/__pycache__/ArticleBookmarkModelSchemeAdmin.cpython-38.pyc
djangoarticle/modeladmins/__pycache__/ArticleModelSchemeAdmin.cpython-38.pyc
djangoarticle/modeladmins/__pycache__/CategoryModelSchemeAdmin.cpython-38.pyc
djangoarticle/modeladmins/__pycache__/__init__.cpython-38.pyc
djangoarticle/modelforms/ArticleModelFormScheme.py
djangoarticle/modelforms/CategoryModelFormScheme.py
djangoarticle/modelforms/__init__.py
djangoarticle-2.2.4.dist-info/License
djangoarticle-2.2.4.dist-info/METADATA
djangoarticle-2.2.4.dist-info/WHEEL
djangoarticle-2.2.4.dist-info/top_level.txt
djangoarticle-2.2.4.dist-info/RECORD
