Metadata-Version: 2.1
Name: djangoarticle
Version: 2.2.4
Summary: Djangoarticle: Django Reusable app to Publish Articles.
Home-page: https://github.com/bhojrampawar/djangoarticle
Author: Bhojram pawar
Author-email: bhojrampawar@hotmail.com
License: MIT
Platform: UNKNOWN
Classifier: Environment :: Web Environment
Classifier: Framework :: Django
Classifier: Framework :: Django :: 2.2
Classifier: Intended Audience :: Developers
Classifier: License :: OSI Approved :: MIT License
Classifier: Operating System :: OS Independent
Classifier: Programming Language :: Python
Classifier: Programming Language :: Python :: 3.5
Classifier: Programming Language :: Python :: 3.6
Classifier: Topic :: Internet :: WWW/HTTP
Classifier: Topic :: Internet :: WWW/HTTP :: Dynamic Content
Requires-Dist: django
Requires-Dist: djangorestframework
Requires-Dist: pillow
Requires-Dist: djangorestframework-simplejwt
Requires-Dist: django-crispy-forms
Requires-Dist: django-filter
Requires-Dist: djangocomment
Requires-Dist: djangotools
Requires-Dist: django-taggit
